partclone/__init__.py
partclone/blockio.py
partclone/fuse.py
partclone/imagebackup.py
partclone/main.py
partclone/ntfsclone.py
partclone/partclone.py
pypartclone-0.1.5.dist-info/LICENSE
pypartclone-0.1.5.dist-info/METADATA
pypartclone-0.1.5.dist-info/WHEEL
pypartclone-0.1.5.dist-info/entry_points.txt
pypartclone-0.1.5.dist-info/top_level.txt
pypartclone-0.1.5.dist-info/RECORD
