Metadata-Version: 2.1
Name: pypartclone
Version: 0.1.5
Summary: Python package to read partclone and ntfsclone backup images & utility to mount images as virtual partitions.
Author-email: joergmlpts <joergmlpts@outlook.com>
Project-URL: Homepage, https://github.com/joergmlpts/pypartclone
Project-URL: Bug Tracker, https://github.com/joergmlpts/pypartclone/issues
Keywords: partclone,ntfsclone,image,backup
Classifier: Development Status :: 4 - Beta
Classifier: Intended Audience :: Developers
Classifier: Intended Audience :: End Users/Desktop
Classifier: Intended Audience :: System Administrators
Classifier: License :: OSI Approved :: MIT License
Classifier: Operating System :: POSIX :: Linux
Classifier: Programming Language :: Python
Classifier: Programming Language :: Python :: 3
Classifier: Programming Language :: Python :: 3 :: Only
Classifier: Programming Language :: Python :: 3.8
Classifier: Programming Language :: Python :: 3.9
Classifier: Programming Language :: Python :: 3.10
Classifier: Programming Language :: Python :: 3.11
Classifier: Programming Language :: Python :: 3.12
Classifier: Programming Language :: Python :: 3.13
Classifier: Topic :: System :: Archiving :: Backup
Classifier: Topic :: Utilities
Requires-Python: >=3.8
License-File: LICENSE
Requires-Dist: lz4
Requires-Dist: tqdm
Requires-Dist: pyfuse3
Requires-Dist: pyzstd
